airavata/__init__.py
airavata/api/Airavata.py
airavata/api/__init__.py
airavata/api/constants.py
airavata/api/ttypes.py
airavata/api/credential/__init__.py
airavata/api/credential/store/CredentialStoreService.py
airavata/api/credential/store/__init__.py
airavata/api/credential/store/constants.py
airavata/api/credential/store/ttypes.py
airavata/api/credential/store/error/__init__.py
airavata/api/credential/store/error/constants.py
airavata/api/credential/store/error/ttypes.py
airavata/api/error/__init__.py
airavata/api/error/constants.py
airavata/api/error/ttypes.py
airavata/api/sharing/SharingRegistryService.py
airavata/api/sharing/__init__.py
airavata/api/sharing/constants.py
airavata/api/sharing/ttypes.py
airavata/api/workflow/Workflow.py
airavata/api/workflow/__init__.py
airavata/api/workflow/constants.py
airavata/api/workflow/ttypes.py
airavata/base/__init__.py
airavata/base/api/BaseAPI.py
airavata/base/api/__init__.py
airavata/base/api/constants.py
airavata/base/api/ttypes.py
airavata/model/__init__.py
airavata/model/constants.py
airavata/model/ttypes.py
airavata/model/appcatalog/__init__.py
airavata/model/appcatalog/accountprovisioning/__init__.py
airavata/model/appcatalog/accountprovisioning/constants.py
airavata/model/appcatalog/accountprovisioning/ttypes.py
airavata/model/appcatalog/appdeployment/__init__.py
airavata/model/appcatalog/appdeployment/constants.py
airavata/model/appcatalog/appdeployment/ttypes.py
airavata/model/appcatalog/appinterface/__init__.py
airavata/model/appcatalog/appinterface/constants.py
airavata/model/appcatalog/appinterface/ttypes.py
airavata/model/appcatalog/computeresource/__init__.py
airavata/model/appcatalog/computeresource/constants.py
airavata/model/appcatalog/computeresource/ttypes.py
airavata/model/appcatalog/gatewaygroups/__init__.py
airavata/model/appcatalog/gatewaygroups/constants.py
airavata/model/appcatalog/gatewaygroups/ttypes.py
airavata/model/appcatalog/gatewayprofile/__init__.py
airavata_python_sdk-2.2.7.dist-info/licenses/LICENSE
airavata_python_sdk-2.2.7.dist-info/METADATA
airavata_python_sdk-2.2.7.dist-info/WHEEL
airavata_python_sdk-2.2.7.dist-info/top_level.txt
airavata_python_sdk-2.2.7.dist-info/RECORD
