Metadata-Version: 2.4
Name: airavata-python-sdk
Version: 2.2.7
Summary: Apache Airavata Python SDK
Author-email: Airavata Developers <dev@airavata.apache.org>
License-Expression: Apache-2.0
Requires-Python: >=3.10
License-File: LICENSE
Requires-Dist: oauthlib
Requires-Dist: requests
Requires-Dist: requests-oauthlib
Requires-Dist: thrift
Requires-Dist: thrift_connector
Requires-Dist: paramiko
Requires-Dist: scp
Requires-Dist: pysftp
Requires-Dist: configparser
Requires-Dist: urllib3
Requires-Dist: pyjwt
Requires-Dist: pydantic
Requires-Dist: rich
Requires-Dist: pandas
Requires-Dist: pyyaml
Provides-Extra: notebook
Requires-Dist: ipywidgets; extra == "notebook"
Requires-Dist: ipython; extra == "notebook"
Dynamic: license-file
